jinjat/__init__.py
jinjat/__main__.py
jinjat/core/__init__.py
jinjat/core/dbt/__init__.py
jinjat/core/dbt/config.py
jinjat/core/dbt/dbt_project.py
jinjat/core/exceptions.py
jinjat/core/generator.py
jinjat/core/log_controller.py
jinjat/core/models.py
jinjat/core/routes/__init__.py
jinjat/core/routes/admin.py
jinjat/core/routes/analysis.py
jinjat/core/schema/__init__.py
jinjat/core/schema/validator.py
jinjat/core/server.py
jinjat/core/util/__init__.py
jinjat/core/util/api.py
jinjat/core/util/filesystem.py
jinjat/core/util/jmespath.py
jinjat/deploy/__init__.py
jinjat/deploy/cloud-run.py
jinjat/deploy/fal.py
jinjat/deploy/modal-client.py
jinjat/jaffle_shop.duckdb
jinjat/main.py
jinjat/playground.py
jinjat/requirements.txt
jinjat-0.6.dist-info/WHEEL
jinjat-0.6.dist-info/LICENSE
jinjat-0.6.dist-info/entry_points.txt
jinjat-0.6.dist-info/METADATA
jinjat-0.6.dist-info/RECORD
